odoo/addons/l10n_es_aeat_mod303_cash_basis/README.rst
odoo/addons/l10n_es_aeat_mod303_cash_basis/__init__.py
odoo/addons/l10n_es_aeat_mod303_cash_basis/__manifest__.py
odoo/addons/l10n_es_aeat_mod303_cash_basis/data/aeat_export_mod303_2018_data.xml
odoo/addons/l10n_es_aeat_mod303_cash_basis/data/tax_code_map_mod303_data.xml
odoo/addons/l10n_es_aeat_mod303_cash_basis/i18n/es.po
odoo/addons/l10n_es_aeat_mod303_cash_basis/i18n/l10n_es_aeat_mod303_cash_basis.pot
odoo/addons/l10n_es_aeat_mod303_cash_basis/models/__init__.py
odoo/addons/l10n_es_aeat_mod303_cash_basis/models/account_move.py
odoo/addons/l10n_es_aeat_mod303_cash_basis/models/account_partial_reconcile.py
odoo/addons/l10n_es_aeat_mod303_cash_basis/models/mod303.py
odoo/addons/l10n_es_aeat_mod303_cash_basis/readme/CONFIGURE.rst
odoo/addons/l10n_es_aeat_mod303_cash_basis/readme/CONTRIBUTORS.rst
odoo/addons/l10n_es_aeat_mod303_cash_basis/readme/DESCRIPTION.rst
odoo/addons/l10n_es_aeat_mod303_cash_basis/readme/USAGE.rst
odoo/addons/l10n_es_aeat_mod303_cash_basis/static/description/icon.png
odoo/addons/l10n_es_aeat_mod303_cash_basis/static/description/icon_source.svg
odoo/addons/l10n_es_aeat_mod303_cash_basis/static/description/index.html
odoo/addons/l10n_es_aeat_mod303_cash_basis/tests/__init__.py
odoo/addons/l10n_es_aeat_mod303_cash_basis/tests/test_l10n_es_aeat_mod303_cash_basis.py
odoo/addons/l10n_es_aeat_mod303_cash_basis/views/mod303_view.xml
odoo12_addon_l10n_es_aeat_mod303_cash_basis-12.0.1.0.0.dist-info/METADATA
odoo12_addon_l10n_es_aeat_mod303_cash_basis-12.0.1.0.0.dist-info/WHEEL
odoo12_addon_l10n_es_aeat_mod303_cash_basis-12.0.1.0.0.dist-info/top_level.txt
odoo12_addon_l10n_es_aeat_mod303_cash_basis-12.0.1.0.0.dist-info/RECORD
